soft_dtw_rust-0.1.2.dist-info/METADATA
soft_dtw_rust-0.1.2.dist-info/WHEEL
soft_dtw_rust-0.1.2.dist-info/license_files/LICENSE
soft_dtw_rust/__init__.py
soft_dtw_rust/soft_dtw_rust.cpython-38-arm-linux-gnueabihf.so
soft_dtw_rust-0.1.2.dist-info/RECORD
