Metadata-Version: 2.3
Name: soft-dtw-rust
Version: 0.1.2
Classifier: Programming Language :: Rust
Classifier: Programming Language :: Python :: Implementation :: CPython
Classifier: Programming Language :: Python :: Implementation :: PyPy
License-File: LICENSE
Summary: A simple implementation of the soft-dtw algorithm in rust with python bindings
Author-email: Alberto Zancanaro <alberto.zancanaro.1@gmail.com>
Requires-Python: >=3.8
Project-URL: Homepage, https://github.com/jesus-333/soft-dtw-rust
Project-URL: Issues, https://github.com/jesus-333/soft-dtw-rust/issues
